sqlite_dissect/__init__.py
sqlite_dissect/_version.py
sqlite_dissect/constants.py
sqlite_dissect/entrypoint.py
sqlite_dissect/exception.py
sqlite_dissect/interface.py
sqlite_dissect/output.py
sqlite_dissect/utilities.py
sqlite_dissect/version_history.py
sqlite_dissect/carving/__init__.py
sqlite_dissect/carving/carved_cell.py
sqlite_dissect/carving/carver.py
sqlite_dissect/carving/rollback_journal_carver.py
sqlite_dissect/carving/signature.py
sqlite_dissect/carving/utilities.py
sqlite_dissect/export/__init__.py
sqlite_dissect/export/case_export.py
sqlite_dissect/export/csv_export.py
sqlite_dissect/export/sqlite_export.py
sqlite_dissect/export/text_export.py
sqlite_dissect/export/xlsx_export.py
sqlite_dissect/file/__init__.py
sqlite_dissect/file/file_handle.py
sqlite_dissect/file/header.py
sqlite_dissect/file/utilities.py
sqlite_dissect/file/version.py
sqlite_dissect/file/version_parser.py
sqlite_dissect/file/database/__init__.py
sqlite_dissect/file/database/database.py
sqlite_dissect/file/database/header.py
sqlite_dissect/file/database/page.py
sqlite_dissect/file/database/payload.py
sqlite_dissect/file/database/utilities.py
sqlite_dissect/file/journal/__init__.py
sqlite_dissect/file/journal/header.py
sqlite_dissect/file/journal/jounal.py
sqlite_dissect/file/schema/__init__.py
sqlite_dissect/file/schema/column.py
sqlite_dissect/file/schema/master.py
sqlite_dissect/file/schema/table.py
sqlite_dissect/file/schema/utilities.py
sqlite_dissect/file/wal/__init__.py
sqlite_dissect/file/wal/commit_record.py
sqlite_dissect/file/wal/frame.py
sqlite_dissect/file/wal/header.py
sqlite_dissect/file/wal/utilities.py
sqlite_dissect/file/wal/wal.py
sqlite_dissect/file/wal_index/__init__.py
sqlite_dissect/file/wal_index/header.py
sqlite_dissect/file/wal_index/wal_index.py
sqlite_dissect-1.0.0.dist-info/LICENSE.txt
sqlite_dissect-1.0.0.dist-info/METADATA
sqlite_dissect-1.0.0.dist-info/WHEEL
sqlite_dissect-1.0.0.dist-info/entry_points.txt
sqlite_dissect-1.0.0.dist-info/top_level.txt
sqlite_dissect-1.0.0.dist-info/RECORD
