Metadata-Version: 2.1
Name: sqlite_dissect
Version: 1.0.0
Summary: This package allows parsing and carving of SQLite files
Home-page: https://github.com/dod-cyber-crime-center/sqlite-dissect
Author: Department of Defense Cyber Crime Center (DC3)
Author-email: dc3.tsd@us.af.mil
Classifier: Programming Language :: Python :: 3
Classifier: Programming Language :: Python :: 3.8
Classifier: Programming Language :: Python :: 3.9
Classifier: Programming Language :: Python :: 3.10
Classifier: Programming Language :: Python :: 3.11
Classifier: Programming Language :: Python :: 3.12
License-File: LICENSE.txt
Requires-Dist: openpyxl
Requires-Dist: ConfigArgParse
